main.py
hayaku-0.1.1.dist-info/DESCRIPTION.rst
hayaku-0.1.1.dist-info/METADATA
hayaku-0.1.1.dist-info/RECORD
hayaku-0.1.1.dist-info/WHEEL
hayaku-0.1.1.dist-info/entry_points.txt
hayaku-0.1.1.dist-info/metadata.json
hayaku-0.1.1.dist-info/top_level.txt
