Metadata-Version: 2.0
Name: hayaku
Version: 0.1.1
Summary: Hayaku - tooling for generating dockerfile
Home-page: UNKNOWN
Author: Alex Myasoedov
Author-email: msoedov@gmail.com
License: MIT
Platform: UNKNOWN
Classifier: Programming Language :: Python
Classifier: Programming Language :: Python :: 2.7
Classifier: Programming Language :: Python :: 3.3
Classifier: Programming Language :: Python :: 3.4
Classifier: Programming Language :: Python :: 3.5
Classifier: Programming Language :: Python :: 3.6
Requires-Dist: fire
Requires-Dist: pigar
